README.md
setup.py
foqus/__init__.py
foqus/cloud_configuration.py
foqus/commons.py
foqus/configuration.py
foqus/customers.py
foqus/database.py
foqus/functions_engine.py
foqus/functions_input.py
foqus/mqueue.py
foqus/payments.py
foqus/pipline_cutomise.py
foqus/request_api.py
foqus/server_apis.py
foqus/stripe_payment.py
foqus/vptree.py
foqus.egg-info/PKG-INFO
foqus.egg-info/SOURCES.txt
foqus.egg-info/dependency_links.txt
foqus.egg-info/top_level.txt