Metadata-Version: 2.1
Name: foqus
Version: 1.0.14.1
Summary: foqus AI package
Home-page: UNKNOWN
Author: Trynfit
Author-email: dbellarej@trynfit.com
License: UNKNOWN
Platform: UNKNOWN
Classifier: Programming Language :: Python :: 3
Classifier: License :: OSI Approved :: MIT License
Classifier: Operating System :: Unix
